nart/__init__.py
nart/main.py
nart/nart.py
nart/datasource/__init__.py
nart/datasource/datasource.py
nart/datasource/builtins/__init__.py
nart/datasource/builtins/htmlparsedatasource.py
nart/model/__init__.py
nart/model/nartdata.py
nart/model/nartitem.py
nart/reader/__init__.py
nart/reader/reader.py
nart/reader/builtins/__init__.py
nart/reader/builtins/csvreader.py
nart/writer/__init__.py
nart/writer/writer.py
nart/writer/builtins/__init__.py
nart/writer/builtins/csvwriter.py
nart/writer/builtins/stdoutwriter.py
nart-1.1.dist-info/LICENSE
nart-1.1.dist-info/METADATA
nart-1.1.dist-info/WHEEL
nart-1.1.dist-info/entry_points.txt
nart-1.1.dist-info/top_level.txt
nart-1.1.dist-info/RECORD
