Metadata-Version: 2.1
Name: nart
Version: 1.1
Summary: NART: Naver RealTime Keyword
Home-page: https://github.com/ocworld/nart
Author: Keunhyun Oh
Author-email: ocworld@gmail.com
License: MIT License
Requires-Dist: requests (==2.21.0)
Requires-Dist: schedule (==0.6.0)
Requires-Dist: beautifulsoup4 (==4.7.1)
